{
  "HR": {
    "rows": [
      {
        "view": "EEG-only",
        "algo": "Ridge",
        "rmse": 10.937907218933105,
        "r2": -0.35777485370635986
      },
      {
        "view": "EEG-only",
        "algo": "RandomForest",
        "rmse": 9.716017342986865,
        "r2": -0.07136098696162962
      },
      {
        "view": "EEG-only",
        "algo": "LightGBM",
        "rmse": 9.383942718491593,
        "r2": 0.0006215940004178355
      },
      {
        "view": "EEG-only",
        "algo": "MLP",
        "rmse": 10.450117111206055,
        "r2": -0.239371657371521
      },
      {
        "view": "Peri+ctx",
        "algo": "Ridge",
        "rmse": 9666.564453125,
        "r2": -1060481.75
      },
      {
        "view": "Peri+ctx",
        "algo": "RandomForest",
        "rmse": 13.354375618513256,
        "r2": -1.0239810405436387
      },
      {
        "view": "Peri+ctx",
        "algo": "LightGBM",
        "rmse": 9.304528694846612,
        "r2": 0.017465012770433108
      },
      {
        "view": "Peri+ctx",
        "algo": "MLP",
        "rmse": 137.444091796875,
        "r2": -213.39340209960938
      },
      {
        "view": "Physio-aware",
        "algo": "Ridge",
        "rmse": 8179.6982421875,
        "r2": -759334.75
      },
      {
        "view": "Physio-aware",
        "algo": "RandomForest",
        "rmse": 12.6969519562445,
        "r2": -0.8296087036129289
      },
      {
        "view": "Physio-aware",
        "algo": "LightGBM",
        "rmse": 9.332706664466933,
        "r2": 0.01150495524755868
      },
      {
        "view": "Physio-aware",
        "algo": "MLP",
        "rmse": 11613.255859375,
        "r2": -1530618.5
      },
      {
        "view": "All",
        "algo": "Ridge",
        "rmse": 9589.822265625,
        "r2": -1043710.375
      },
      {
        "view": "All",
        "algo": "RandomForest",
        "rmse": 11.42012495727925,
        "r2": -0.4801338023351944
      },
      {
        "view": "All",
        "algo": "LightGBM",
        "rmse": 9.406023675538986,
        "r2": -0.004087129198884654
      },
      {
        "view": "All",
        "algo": "MLP",
        "rmse": 9962.5322265625,
        "r2": -1126414.875
      },
      {
        "view": "All+temporal",
        "algo": "LightGBM",
        "rmse": 9.393221479628208,
        "r2": -0.0013557364928387106
      }
    ],
    "best": {
      "view": "Peri+ctx",
      "algo": "LightGBM",
      "rmse": 9.304528694846612,
      "r2": 0.017465012770433108
    },
    "val_std": 9.386860847473145
  },
  "GSR": {
    "rows": [
      {
        "view": "EEG-only",
        "algo": "Ridge",
        "rmse": 1.0698694495658856e-05,
        "r2": -0.10459864139556885
      },
      {
        "view": "EEG-only",
        "algo": "RandomForest",
        "rmse": 1.0253526798090103e-05,
        "r2": -0.014587306087125107
      },
      {
        "view": "EEG-only",
        "algo": "LightGBM",
        "rmse": 1.0210120265218022e-05,
        "r2": -0.006015328687665855
      },
      {
        "view": "EEG-only",
        "algo": "MLP",
        "rmse": 1.0838113666977733e-05,
        "r2": -0.13357508182525635
      },
      {
        "view": "Peri+ctx",
        "algo": "Ridge",
        "rmse": 0.0003872074303217232,
        "r2": -1445.87255859375
      },
      {
        "view": "Peri+ctx",
        "algo": "RandomForest",
        "rmse": 1.1929761652152739e-05,
        "r2": -0.37342964265975276
      },
      {
        "view": "Peri+ctx",
        "algo": "LightGBM",
        "rmse": 1.0276416007307708e-05,
        "r2": -0.01912214026401693
      },
      {
        "view": "Peri+ctx",
        "algo": "MLP",
        "rmse": 0.0009673713939264417,
        "r2": -9029.865234375
      },
      {
        "view": "Physio-aware",
        "algo": "Ridge",
        "rmse": 0.0004554820479825139,
        "r2": -2001.098388671875
      },
      {
        "view": "Physio-aware",
        "algo": "RandomForest",
        "rmse": 1.1851661212301668e-05,
        "r2": -0.35550567309345094
      },
      {
        "view": "Physio-aware",
        "algo": "LightGBM",
        "rmse": 1.0290122877197752e-05,
        "r2": -0.021842600510942667
      },
      {
        "view": "Physio-aware",
        "algo": "MLP",
        "rmse": 0.0016221284167841077,
        "r2": -25391.9609375
      },
      {
        "view": "All",
        "algo": "Ridge",
        "rmse": 0.0007005659863352776,
        "r2": -4735.31884765625
      },
      {
        "view": "All",
        "algo": "RandomForest",
        "rmse": 1.0881694720419358e-05,
        "r2": -0.1427098172132819
      },
      {
        "view": "All",
        "algo": "LightGBM",
        "rmse": 1.0272394363924465e-05,
        "r2": -0.018324635796967526
      },
      {
        "view": "All",
        "algo": "MLP",
        "rmse": 0.0007057442562654614,
        "r2": -4805.595703125
      },
      {
        "view": "All+temporal",
        "algo": "LightGBM",
        "rmse": 1.0250893590601372e-05,
        "r2": -0.014066260812492626
      }
    ],
    "best": {
      "view": "EEG-only",
      "algo": "LightGBM",
      "rmse": 1.0210120265218022e-05,
      "r2": -0.006015328687665855
    },
    "val_std": 1.0179549462918658e-05
  }
}